log_wmse_audio_quality/__init__.py
log_wmse_audio_quality/constants.py
log_wmse_audio_quality/filter_ir.pkl
log_wmse_audio_quality/freq_weighting_filter.py
log_wmse_audio_quality/metric.py
log_wmse_audio_quality/utils.py
log_wmse_audio_quality-0.2.0.dist-info/LICENSE
log_wmse_audio_quality-0.2.0.dist-info/METADATA
log_wmse_audio_quality-0.2.0.dist-info/WHEEL
log_wmse_audio_quality-0.2.0.dist-info/top_level.txt
log_wmse_audio_quality-0.2.0.dist-info/RECORD
