Metadata-Version: 2.1
Name: log-wmse-audio-quality
Version: 0.2.0
Summary: logWMSE is an audio quality metric with support for digital silence target. Useful for evaluating audio source separation systems, even when there are many audio tracks or stems.
Home-page: https://github.com/nomonosound/log-wmse-audio-quality
Author: Iver Jordal
License: Apache 2.0
Project-URL: Issue Tracker, https://github.com/nomonosound/log-wmse-audio-quality/issues
Classifier: Programming Language :: Python :: 3
Classifier: Operating System :: OS Independent
Classifier: Development Status :: 3 - Alpha
Classifier: Intended Audience :: Developers
Classifier: Intended Audience :: Science/Research
Classifier: Topic :: Multimedia
Classifier: Topic :: Multimedia :: Sound/Audio
Classifier: Topic :: Scientific/Engineering
Classifier: Topic :: Scientific/Engineering :: Artificial Intelligence
Requires-Python: >=3.9
License-File: LICENSE
Requires-Dist: numpy <3,>=1.22
Requires-Dist: soxr <1,>=0.3.2
Requires-Dist: scipy <2,>=1.3
